matsengrp_rich_example/__init__.py
matsengrp_rich_example-0.1.9.dist-info/METADATA
matsengrp_rich_example-0.1.9.dist-info/WHEEL
matsengrp_rich_example-0.1.9.dist-info/entry_points.txt
matsengrp_rich_example-0.1.9.dist-info/RECORD
