Metadata-Version: 2.4
Name: matsengrp_rich_example
Version: 0.1.9
Requires-Python: <=3.12,>=3.9
Requires-Dist: rich
